{"id":"monero","symbol":"xmr","name":"Monero","localization":{"en":"Monero","de":"Monero","es":"Monero","fr":"Monero","it":"Monero","pl":"Monero","ro":"Monero","hu":"Monero","nl":"Monero","pt":"Monero","sv":"Monero","vi":"Monero","tr":"Monero","ru":"Монеро","ja":"モネロ","zh":"门罗币","zh-tw":"門羅幣","ko":"모네로","ar":"Monero","th":"Monero","id":"Monero"},"image":{"thumb":"https://assets.coingecko.com/coins/images/69/thumb/monero_logo.png?1547033729","small":"https://assets.coingecko.com/coins/images/69/small/monero_logo.png?1547033729"},"market_data":{"current_price":{"aud":null,"bdt":148.2847153395504,"bhd":0.72115028062896,"bmd":1.91272848,"brl":null,"btc":0.00308256,"cad":2.074252774464,"chf":1.720581109728,"cny":12.0159498888,"dkk":null,"eur":1.402972930944,"gbp":1.141459021248,"hkd":14.8297491888,"idr":null,"inr":null,"jpy":194.630454656352,"krw":1952.357006085408,"ltc":0.1748474191718661,"mmk":1849.8474929654305,"mxn":null,"myr":null,"ngn":311.12097355826444,"nzd":null,"php":null,"pln":null,"rub":66.69932818224,"sek":12.7836383376,"sgd":2.399080000512,"twd":57.64429739328,"uah":22.5630042049152,"usd":1.91272848,"vef":12.04011699582432,"vnd":40449.96746989842,"xag":null,"xau":null,"xdr":1.2467336856,"zar":null},"market_cap":{"aud":null,"brl":null,"btc":null,"cad":null,"chf":null,"cny":null,"dkk":null,"eur":null,"gbp":null,"hkd":null,"idr":null,"inr":null,"jpy":null,"krw":null,"mxn":null,"myr":null,"ngn":343791933.760585,"nzd":null,"php":null,"pln":null,"rub":null,"sek":null,"sgd":null,"twd":null,"uah":24932355.920399997,"usd":2113585.0,"vnd":44697637635.87881,"xag":null,"xau":null,"xdr":null,"zar":null},"total_volume":{"aud":121508.4654403831,"bdt":8731422.058908472,"bhd":42463.361470892574,"bmd":112626.84494981148,"brl":253331.29915636813,"btc":181.509822642726,"cad":122137.85075039674,"chf":101312.66611814659,"cny":707533.0028288083,"dkk":619472.0784460909,"eur":82611.00120295823,"gbp":67212.32498334633,"hkd":873217.4378098716,"idr":1321178805.4643226,"inr":6692689.624949508,"jpy":11460389.84011587,"krw":114960284.27989915,"ltc":10295.50894173148,"mmk":108924235.16954954,"mxn":1454409.8388508845,"myr":363497.28838373633,"ngn":18319679.98384227,"nzd":133154.68019060834,"php":4958577.414887016,"pln":343852.5347320609,"rub":3927444.4710718878,"sek":752736.6628343094,"sgd":141264.59351923212,"twd":3394258.731774501,"uah":1328573.293470764,"usd":112626.84494981148,"vef":708956.0302183066,"vnd":2381808114.4779983,"xag":6037.942401192545,"xau":90.46449560513464,"xdr":73411.19399329393,"zar":1193946.855404043}},"community_data":{"facebook_likes":null,"twitter_followers":203,"reddit_average_posts_48h":0.229,"reddit_average_comments_48h":3.521,"reddit_subscribers":230,"reddit_accounts_active_48h":"6.0"},"developer_data":{"forks":null,"stars":null,"subscribers":null,"total_issues":null,"closed_issues":null,"pull_requests_merged":null,"pull_request_contributors":null,"code_additions_deletions_4_weeks":{"additions":null,"deletions":null},"commit_count_4_weeks":null},"public_interest_stats":{"alexa_rank":null,"bing_matches":null}}